cuke2confluence/__init__.py
cuke2confluence/cli.py
cuke2confluence/render.py
cuke2confluence/templates/feature_details.xml.j2
cuke2confluence/templates/features_table.xml.j2
cuke2confluence/templates/page.xml.j2
cuke2confluence/templates/scenario_block.xml.j2
cuke2confluence/templates/steps_table.xml.j2
cuke2confluence/templates/summary_table.xml.j2
cuke2confluence-1.1.0.dist-info/METADATA
cuke2confluence-1.1.0.dist-info/WHEEL
cuke2confluence-1.1.0.dist-info/entry_points.txt
cuke2confluence-1.1.0.dist-info/licenses/LICENSE
cuke2confluence-1.1.0.dist-info/RECORD
