Metadata-Version: 2.4
Name: cuke2confluence
Version: 1.1.0
Summary: Render Cucumber JSON to Confluence Storage Format (Jinja2 templates) and optional publish.
Project-URL: Homepage, https://github.com/sjacobs/cuke2conf
Project-URL: Bug Tracker, https://github.com/sjacobs/cuke2conf/issues
Author-email: Steffen Jacobs <kontakt@steffenjacobs.de>
License-Expression: MIT
License-File: LICENSE
Keywords: bdd,confluence,cucumber,reports
Requires-Python: >=3.9
Requires-Dist: jinja2<4,>=3.1
Provides-Extra: publish
Requires-Dist: requests<3,>=2.31; extra == 'publish'
Provides-Extra: test
Requires-Dist: pytest-cov>=5; extra == 'test'
Requires-Dist: pytest>=8; extra == 'test'
